[
  {
    "name": "imath",
    "full_name": "imath",
    "tap": "homebrew/core",
    "oldname": null,
    "oldnames": [

    ],
    "aliases": [

    ],
    "versioned_formulae": [

    ],
    "desc": "Library of 2D and 3D vector, matrix, and math operations",
    "license": "BSD-3-Clause",
    "homepage": "https://www.openexr.com/",
    "versions": {
      "stable": "3.1.9",
      "head": null,
      "bottle": true
    },
    "urls": {
      "stable": {
        "url": "https://github.com/AcademySoftwareFoundation/Imath/archive/refs/tags/v3.1.9.tar.gz",
        "tag": null,
        "revision": null,
        "checksum": "f1d8aacd46afed958babfced3190d2d3c8209b66da451f556abd6da94c165cf3"
      }
    },
    "revision": 0,
    "version_scheme": 0,
    "bottle": {
      "stable": {
        "rebuild": 0,
        "root_url": "https://ghcr.io/v2/homebrew/core",
        "files": {
          "arm64_ventura": {
            "cellar": ":any",
            "url": "https://ghcr.io/v2/homebrew/core/imath/blobs/sha256:089d0a19694cd8bb2687be2d573e9f5aa1ee75f9173033bfc0aa2c4879d69e49",
            "sha256": "089d0a19694cd8bb2687be2d573e9f5aa1ee75f9173033bfc0aa2c4879d69e49"
          },
          "arm64_monterey": {
            "cellar": ":any",
            "url": "https://ghcr.io/v2/homebrew/core/imath/blobs/sha256:cd78bb2314109596f4dfd8d30c8ddc2c93ece0605762e42ef1d610b0f99fd4d5",
            "sha256": "cd78bb2314109596f4dfd8d30c8ddc2c93ece0605762e42ef1d610b0f99fd4d5"
          },
          "arm64_big_sur": {
            "cellar": ":any",
            "url": "https://ghcr.io/v2/homebrew/core/imath/blobs/sha256:8beb6dbb10be5ff784de51ea573d7b6c5617d1474b2c018a8fc41af624a5f419",
            "sha256": "8beb6dbb10be5ff784de51ea573d7b6c5617d1474b2c018a8fc41af624a5f419"
          },
          "ventura": {
            "cellar": ":any",
            "url": "https://ghcr.io/v2/homebrew/core/imath/blobs/sha256:4cf74522f152f13e85353c2c4af9ba195fb7f75fe9fd1f4fcba590d544bb35ac",
            "sha256": "4cf74522f152f13e85353c2c4af9ba195fb7f75fe9fd1f4fcba590d544bb35ac"
          },
          "monterey": {
            "cellar": ":any",
            "url": "https://ghcr.io/v2/homebrew/core/imath/blobs/sha256:fe2514670ff94bb4e331ee2d79fc63c87072daedcc3a0dd53dfeec3f870aa170",
            "sha256": "fe2514670ff94bb4e331ee2d79fc63c87072daedcc3a0dd53dfeec3f870aa170"
          },
          "big_sur": {
            "cellar": ":any",
            "url": "https://ghcr.io/v2/homebrew/core/imath/blobs/sha256:4b20276f002c8cf184c4c2ad8d1eb78ee5933e9429424321e2002e583ba25fed",
            "sha256": "4b20276f002c8cf184c4c2ad8d1eb78ee5933e9429424321e2002e583ba25fed"
          },
          "x86_64_linux": {
            "cellar": ":any_skip_relocation",
            "url": "https://ghcr.io/v2/homebrew/core/imath/blobs/sha256:64f31ec84b72c1343a1386abf63ab91c6ed7fca57304e9463dade8dd469ea072",
            "sha256": "64f31ec84b72c1343a1386abf63ab91c6ed7fca57304e9463dade8dd469ea072"
          }
        }
      }
    },
    "keg_only": false,
    "keg_only_reason": null,
    "options": [

    ],
    "build_dependencies": [
      "cmake"
    ],
    "dependencies": [

    ],
    "test_dependencies": [

    ],
    "recommended_dependencies": [

    ],
    "optional_dependencies": [

    ],
    "uses_from_macos": [

    ],
    "uses_from_macos_bounds": [

    ],
    "requirements": [

    ],
    "conflicts_with": [

    ],
    "conflicts_with_reasons": [

    ],
    "link_overwrite": [
      "lib/libImath.dylib",
      "lib/libImath.so"
    ],
    "caveats": null,
    "installed": [
      {
        "version": "3.1.7",
        "used_options": [

        ],
        "built_as_bottle": true,
        "poured_from_bottle": true,
        "time": 1679300874,
        "runtime_dependencies": [

        ],
        "installed_as_dependency": true,
        "installed_on_request": false
      },
      {
        "version": "3.1.9",
        "used_options": [

        ],
        "built_as_bottle": true,
        "poured_from_bottle": true,
        "time": 1687595080,
        "runtime_dependencies": [

        ],
        "installed_as_dependency": true,
        "installed_on_request": false
      }
    ],
    "linked_keg": "3.1.9",
    "pinned": false,
    "outdated": false,
    "deprecated": false,
    "deprecation_date": null,
    "deprecation_reason": null,
    "disabled": false,
    "disable_date": null,
    "disable_reason": null,
    "post_install_defined": false,
    "service": null,
    "tap_git_head": "3d9c544ead07ae31eb5497c1cd145119171a043a",
    "ruby_source_path": "Formula/imath.rb",
    "ruby_source_checksum": {
      "sha256": "1a86f6313b0db2a7887e67ab060947f6db0d758de91925258f07c4e1efc66f12"
    }
  }
]
